xutility/__init__.py
xutility/chrono.py
xutility/coro.py
xutility/data_container.py
xutility/env.py
xutility/exception.py
xutility/logger.py
xutility/numeric.py
xutility/py.typed
xutility/xcom.py
xutility-0.3.1.dist-info/METADATA
xutility-0.3.1.dist-info/WHEEL
xutility-0.3.1.dist-info/licenses/LICENSE
xutility-0.3.1.dist-info/RECORD
